clip2classdist/__init__.py
clip2classdist/compute.py
tests/__init__.py
tests/test_compute_cluster_centers.py
tests/test_compute_cluster_radii.py
tests/test_compute_dot_product_distribution.py
clip2classdist-0.1.0.dist-info/LICENSE
clip2classdist-0.1.0.dist-info/METADATA
clip2classdist-0.1.0.dist-info/WHEEL
clip2classdist-0.1.0.dist-info/entry_points.txt
clip2classdist-0.1.0.dist-info/top_level.txt
clip2classdist-0.1.0.dist-info/RECORD
