Metadata-Version: 2.1
Name: clip2classdist
Version: 0.1.0
Summary: A Python script that analyzes image classes using OpenAI CLIP model
Home-page: https://github.com/ternaus/clip2classdist
Author: Vladimir Iglovikov
Author-email: iglovikov@gmail.com
Classifier: Development Status :: 3 - Alpha
Classifier: License :: OSI Approved :: MIT License
Classifier: Programming Language :: Python :: 3
Classifier: Programming Language :: Python :: 3.6
Classifier: Programming Language :: Python :: 3.7
Classifier: Programming Language :: Python :: 3.8
License-File: LICENSE
Requires-Dist: torch
Requires-Dist: faiss-cpu (>=1.7.3)
Requires-Dist: torch (>=2.0.0)
Requires-Dist: torchvision (>=0.15.1)
